awesome_panel/__init__.py
awesome_panel/assets/__init__.py
awesome_panel/assets/svg.py
awesome_panel/assets/__pycache__/__init__.cpython-39.pyc
awesome_panel/assets/__pycache__/svg.cpython-39.pyc
awesome_panel/assets/css/__init__.py
awesome_panel/assets/csv/__init__.py
awesome_panel/assets/csv/bootstrap_dashboard_chart.csv
awesome_panel/assets/csv/bootstrap_dashboard_table.csv
awesome_panel/assets/csv/dashboard_A.csv
awesome_panel/assets/csv/dashboard_B.csv
awesome_panel/assets/csv/epl_top_strikers_2020_2021.csv
awesome_panel/assets/csv/global_power_plant_database.csv
awesome_panel/assets/csv/kickstarter_dashboard.csv
awesome_panel/assets/csv/perspective_viewer_data.csv
awesome_panel/assets/csv/renewable_power_plants_DK.csv
awesome_panel/assets/csv/tabulator_data.csv
awesome_panel/assets/csv/__pycache__/__init__.cpython-39.pyc
awesome_panel/assets/html/__init__.py
awesome_panel/assets/html/menu.html
awesome_panel/assets/html/menu_fast_other.html
awesome_panel/assets/html/shoelace_template.html
awesome_panel/assets/html/__pycache__/__init__.cpython-39.pyc
awesome_panel/assets/images/__init__.py
awesome_panel/assets/markdown/__init__.py
awesome_panel/assets/markdown/about.md
awesome_panel/assets/markdown/home.md
awesome_panel/assets/markdown/__pycache__/__init__.cpython-39.pyc
awesome_panel/assets/yaml/__init__.py
awesome_panel/assets/yaml/awesome_list.yaml
awesome_panel/assets/yaml/config.yaml
awesome_panel/assets/yaml/__pycache__/__init__.cpython-39.pyc
awesome_panel/config/__init__.py
awesome_panel-20221019.3.dist-info/LICENSE
awesome_panel-20221019.3.dist-info/METADATA
awesome_panel-20221019.3.dist-info/WHEEL
awesome_panel-20221019.3.dist-info/top_level.txt
awesome_panel-20221019.3.dist-info/RECORD
