Metadata-Version: 2.1
Name: awesome-panel
Version: 20221019.3
Summary: This package makes it super simple to do exploratory data analysis and develop high-quality Panel data apps ...
Author: awesome-panel
License: MIT License        
Project-URL: repository, https://github.com/awesome-panel/awesome-panel
Keywords: python,holoviz,panel,dataviz,dataapp,dashboard,datascience,analytics
Classifier: License :: OSI Approved :: MIT License
Classifier: Development Status :: 3 - Alpha
Classifier: Programming Language :: Python :: 3
Classifier: Programming Language :: Python :: 3.7
Classifier: Programming Language :: Python :: 3.8
Classifier: Programming Language :: Python :: 3.9
Classifier: Programming Language :: Python :: 3.10
Classifier: Operating System :: OS Independent
Classifier: Intended Audience :: Developers
Classifier: Intended Audience :: Education
Classifier: Intended Audience :: Financial and Insurance Industry
Classifier: Intended Audience :: Healthcare Industry
Classifier: Intended Audience :: Information Technology
Classifier: Intended Audience :: Legal Industry
Classifier: Intended Audience :: Other Audience
Classifier: Intended Audience :: Science/Research
Classifier: Natural Language :: English
Classifier: Topic :: Office/Business :: Financial
Classifier: Topic :: Office/Business
Classifier: Topic :: Scientific/Engineering :: Information Analysis
Classifier: Topic :: Scientific/Engineering :: Visualization
Classifier: Topic :: Scientific/Engineering
Classifier: Topic :: Software Development :: Libraries
Requires-Python: >=3.7
License-File: LICENSE
Requires-Dist: bokeh (<3.0)
Requires-Dist: panel (<1.0)
Provides-Extra: dev
Requires-Dist: awesome-panel-cli[dev] ; extra == 'dev'
Requires-Dist: selenium (==4.5.0) ; extra == 'dev'
Requires-Dist: locust (==2.12.2) ; extra == 'dev'
Provides-Extra: docs
Requires-Dist: Sphinx ; extra == 'docs'
Requires-Dist: sphinx-rtd-theme ; extra == 'docs'
Requires-Dist: recommonmark ; extra == 'docs'
Requires-Dist: sphinx-autobuild ; extra == 'docs'
Requires-Dist: sphinxcontrib-napoleon ; extra == 'docs'
Requires-Dist: sphinx-markdown-tables ; extra == 'docs'
Requires-Dist: doc8 ; extra == 'docs'
Provides-Extra: examples
Requires-Dist: altair ; extra == 'examples'
Requires-Dist: awesome-panel-cli ; extra == 'examples'
Requires-Dist: awesome-panel-extensions (==20221019.2) ; extra == 'examples'
Requires-Dist: bloxs ; extra == 'examples'
Requires-Dist: datashader ; extra == 'examples'
Requires-Dist: diskcache ; extra == 'examples'
Requires-Dist: fitparse ; extra == 'examples'
Requires-Dist: folium ; extra == 'examples'
Requires-Dist: holoviews ; extra == 'examples'
Requires-Dist: hvplot ; extra == 'examples'
Requires-Dist: ipykernel ; extra == 'examples'
Requires-Dist: ipywidgets-bokeh ; extra == 'examples'
Requires-Dist: lxml ; extra == 'examples'
Requires-Dist: ipysheet ; extra == 'examples'
Requires-Dist: ipywidgets ; extra == 'examples'
Requires-Dist: jinja2 ; extra == 'examples'
Requires-Dist: jupyter ; extra == 'examples'
Requires-Dist: notebook ; extra == 'examples'
Requires-Dist: pandas-profiling ; extra == 'examples'
Requires-Dist: pandas ; extra == 'examples'
Requires-Dist: panel-chemistry (==0.2.2) ; extra == 'examples'
Requires-Dist: panel-highcharts (==20221018.1) ; extra == 'examples'
Requires-Dist: param ; extra == 'examples'
Requires-Dist: Pillow ; extra == 'examples'
Requires-Dist: plotly ; extra == 'examples'
Requires-Dist: plotnine ; extra == 'examples'
Requires-Dist: pooch ; extra == 'examples'
Requires-Dist: py3Dmol ; extra == 'examples'
Requires-Dist: pydeck ; extra == 'examples'
Requires-Dist: pyecharts ; extra == 'examples'
Requires-Dist: pyvista ; extra == 'examples'
Requires-Dist: scikit-learn ; extra == 'examples'
Requires-Dist: seaborn ; extra == 'examples'
Requires-Dist: statsmodels ; extra == 'examples'
Requires-Dist: streamz ; extra == 'examples'
Requires-Dist: tensorflow ; extra == 'examples'
Requires-Dist: torch ; extra == 'examples'
Requires-Dist: torchvision ; extra == 'examples'
Requires-Dist: vega-datasets ; extra == 'examples'
Requires-Dist: vtk ; extra == 'examples'
Requires-Dist: xarray ; extra == 'examples'
Requires-Dist: xlrd ; extra == 'examples'
Requires-Dist: yahooquery ; extra == 'examples'
Requires-Dist: yfinance ; extra == 'examples'
Requires-Dist: geopandas ; (platform_system != "Windows") and extra == 'examples'
